Adafruit_CharLCD-1.1.1.dist-info/metadata.json
Adafruit_CharLCD-1.1.1.dist-info/METADATA
Adafruit_CharLCD-1.1.1.dist-info/RECORD
Adafruit_CharLCD-1.1.1.dist-info/WHEEL
Adafruit_CharLCD-1.1.1.dist-info/DESCRIPTION.rst
Adafruit_CharLCD-1.1.1.dist-info/dependency_links.txt
Adafruit_CharLCD-1.1.1.dist-info/top_level.txt
Adafruit_CharLCD/Adafruit_CharLCD.py
Adafruit_CharLCD/__init__.py
