Metadata-Version: 1.1
Name: Adafruit_CharLCD
Version: 1.1.1
Summary: Library to drive character LCD display and plate.
Home-page: https://github.com/adafruit/Adafruit_Python_CharLCD/
Author: Tony DiCola
Author-email: tdicola@adafruit.com
License: MIT
Platform: UNKNOWN
Classifier: Development Status :: 4 - Beta
Classifier: Operating System :: POSIX :: Linux
Classifier: License :: OSI Approved :: MIT License
Classifier: Intended Audience :: Developers
Classifier: Programming Language :: Python :: 2.7
Classifier: Programming Language :: Python :: 3
Classifier: Topic :: Software Development
Classifier: Topic :: System :: Hardware
